kuro/__init__.py
kuro/constants.py
kuro/errors.py
kuro/types.py
kuro/client/__init__.py
kuro/client/clients.py
kuro/client/decorators.py
kuro/client/routes.py
kuro/client/components/base.py
kuro/client/components/gacha.py
kuro/client/components/game.py
kuro/client/components/announcements/__init__.py
kuro/client/components/announcements/client.py
kuro/client/components/announcements/subclients/__init__.py
kuro/client/components/announcements/subclients/game.py
kuro/client/components/announcements/subclients/launcher.py
kuro/client/components/auth/__init__.py
kuro/client/components/auth/client.py
kuro/client/components/auth/subclients/__init__.py
kuro/client/components/auth/subclients/game.py
kuro/client/components/auth/subclients/web.py
kuro/filters/__init__.py
kuro/filters/gacha.py
kuro/models/__init__.py
kuro/models/assets.py
kuro/models/base.py
kuro/models/gacha.py
kuro/models/game.py
kuro/models/announcements/__init__.py
kuro/models/announcements/game.py
kuro/models/announcements/launcher.py
kuro/models/auth/__init__.py
kuro/models/auth/game.py
kuro/models/auth/web.py
kuro/utility/gacha.py
kuro/utility/auth/__init__.py
kuro/utility/auth/crypto.py
kuro/utility/geetest/__init__.py
kuro/utility/geetest/server.py
kuro/utility/geetest/utility.py
kuro_py-0.7.1.dist-info/METADATA
kuro_py-0.7.1.dist-info/WHEEL
kuro_py-0.7.1.dist-info/licenses/LICENSE
kuro_py-0.7.1.dist-info/RECORD
