Metadata-Version: 2.4
Name: kuro.py
Version: 0.7.1
Summary: Async API wrapper for KuroBBS written in Python.
Project-URL: Homepage, https://github.com/Wuthery/kuro.py
Project-URL: Repository, https://github.com/Wuthery/kuro.py
Project-URL: Documentation, https://github.com/Wuthery/kuro.py
Author-email: JokelBaf <jokelbaf@gmail.com>
Maintainer-email: JokelBaf <jokelbaf@gmail.com>, seriaati <seria.ati@gmail.com>
License-Expression: GPL-3.0
License-File: LICENSE
Keywords: api,kuro,kurobbs,wraper,wuwa
Requires-Python: >=3.10
Requires-Dist: aiohttp>=3.8.4
Requires-Dist: pydantic>=2.12.5
Provides-Extra: caching
Requires-Dist: aiocache; extra == 'caching'
Provides-Extra: test
Requires-Dist: pytest; extra == 'test'
Requires-Dist: pytest-asyncio; extra == 'test'
Requires-Dist: python-dotenv; extra == 'test'
